{"cameraMode":{"drawMode":0,"name":"Shaded","section":"Shading Mode"},"sceneLighting":true,"audioPlay":false,"sceneViewState":{"m_AlwaysRefresh":false,"showFog":true,"showSkybox":true,"showFlares":true,"showImageEffects":true,"showParticleSystems":true,"showVisualEffectGraphs":true,"m_FxEnabled":true},"in2DMode":false,"pivot":{"x":96.9148178100586,"y":333.2701110839844,"z":179.18161010742188},"rotation":{"x":0.21028819680213929,"y":-0.06886126101016998,"z":0.014843474142253399,"w":0.9751248359680176},"size":47.51839065551758,"orthographic":false}